pyopenjtalk/__init__.py
pyopenjtalk/htsengine.cp312-win_amd64.pyd
pyopenjtalk/openjtalk.cp312-win_amd64.pyd
pyopenjtalk/utils.py
pyopenjtalk/version.py
pyopenjtalk/htsvoice/LICENSE_mei_normal.htsvoice
pyopenjtalk/htsvoice/README.md
pyopenjtalk/htsvoice/mei_normal.htsvoice
pyopenjtalk_dict-0.3.4.dev2.dist-info/LICENSE.md
pyopenjtalk_dict-0.3.4.dev2.dist-info/METADATA
pyopenjtalk_dict-0.3.4.dev2.dist-info/WHEEL
pyopenjtalk_dict-0.3.4.dev2.dist-info/top_level.txt
pyopenjtalk_dict-0.3.4.dev2.dist-info/RECORD
