Metadata-Version: 2.1
Name: pyopenjtalk-dict
Version: 0.3.4.dev2
Summary: A python wrapper for OpenJTalk
Home-page: https://github.com/litagin02/pyopenjtalk
Author: Ryuichi Yamamoto
Author-email: zryuichi@gmail.com
License: MIT
Keywords: OpenJTalk,Research
Platform: UNKNOWN
Classifier: Operating System :: POSIX
Classifier: Operating System :: Unix
Classifier: Operating System :: MacOS
Classifier: Operating System :: Microsoft :: Windows
Classifier: Programming Language :: Cython
Classifier: Programming Language :: Python
Classifier: Programming Language :: Python :: 3
Classifier: Programming Language :: Python :: 3.7
Classifier: Programming Language :: Python :: 3.8
Classifier: Programming Language :: Python :: 3.9
Classifier: Programming Language :: Python :: 3.10
Classifier: License :: OSI Approved :: MIT License
Classifier: Topic :: Scientific/Engineering
Classifier: Topic :: Software Development
Classifier: Intended Audience :: Science/Research
Classifier: Intended Audience :: Developers
License-File: LICENSE.md
Requires-Dist: numpy >=1.20.0
Requires-Dist: six
Requires-Dist: tqdm
Provides-Extra: dev
Requires-Dist: cython <3.0.0,>=0.21.0 ; extra == 'dev'
Requires-Dist: pysen ; extra == 'dev'
Requires-Dist: types-setuptools ; extra == 'dev'
Requires-Dist: mypy <=0.910 ; extra == 'dev'
Requires-Dist: black <=20.8,>=19.19b0 ; extra == 'dev'
Requires-Dist: click <8.1.0 ; extra == 'dev'
Requires-Dist: flake8 <4,>=3.7 ; extra == 'dev'
Requires-Dist: flake8-bugbear ; extra == 'dev'
Requires-Dist: isort <5.2.0,>=4.3 ; extra == 'dev'
Requires-Dist: types-decorator ; extra == 'dev'
Requires-Dist: importlib-metadata <5.0 ; extra == 'dev'
Provides-Extra: docs
Requires-Dist: sphinx-rtd-theme ; extra == 'docs'
Requires-Dist: nbsphinx >=0.8.6 ; extra == 'docs'
Requires-Dist: Jinja2 >=3.0.1 ; extra == 'docs'
Requires-Dist: pandoc ; extra == 'docs'
Requires-Dist: ipython ; extra == 'docs'
Requires-Dist: jupyter ; extra == 'docs'
Provides-Extra: marine
Requires-Dist: marine >=0.0.5 ; extra == 'marine'
Provides-Extra: test
Requires-Dist: pytest ; extra == 'test'
Requires-Dist: scipy ; extra == 'test'
